cfscanner/__init__.py
cfscanner/__main__.py
cfscanner/_version.py
cfscanner/main.py
cfscanner/args/__init__.py
cfscanner/args/parser.py
cfscanner/args/testconfig.py
cfscanner/report/__init__.py
cfscanner/report/colors.py
cfscanner/report/logging_setup.py
cfscanner/report/print.py
cfscanner/report/result.py
cfscanner/speedtest/__init__.py
cfscanner/speedtest/conduct.py
cfscanner/speedtest/download.py
cfscanner/speedtest/fronting.py
cfscanner/speedtest/tools.py
cfscanner/speedtest/upload.py
cfscanner/subnets/__init__.py
cfscanner/subnets/cidr.py
cfscanner/subnets/regex.py
cfscanner/utils/__init__.py
cfscanner/utils/decorators.py
cfscanner/utils/exceptions.py
cfscanner/utils/os.py
cfscanner/utils/random.py
cfscanner/utils/requests.py
cfscanner/utils/socket.py
cfscanner/xray/__init__.py
cfscanner/xray/binary.py
cfscanner/xray/config.py
cfscanner/xray/service.py
cfscanner/xray/templates.py
cfscanner-1.5.3.dist-info/licenses/LICENSE
cfscanner-1.5.3.dist-info/METADATA
cfscanner-1.5.3.dist-info/WHEEL
cfscanner-1.5.3.dist-info/entry_points.txt
cfscanner-1.5.3.dist-info/top_level.txt
cfscanner-1.5.3.dist-info/RECORD
