Metadata-Version: 2.4
Name: cfscanner
Version: 1.5.3
Summary: Cloudflare's edge IPs scanner to locate ones that are viable for use with v2ray/xray
Author-email: tempookian <tempookian@gmail.com>, Morteza Bashsiz <morteza.bashsiz@gmail.com>
Project-URL: Homepage, https://github.com/MortezaBashsiz/CFScanner/tree/main/python
Project-URL: Bug Tracker, https://github.com/MortezaBashsiz/CFScanner/issues
Classifier: Programming Language :: Python :: 3
Classifier: License :: OSI Approved :: GNU General Public License v3 (GPLv3)
Classifier: Operating System :: OS Independent
Requires-Python: >=3.8
License-File: LICENSE
Requires-Dist: requests>=2.28.2
Requires-Dist: pysocks>=1.7.1
Requires-Dist: rich>=13.3.3
Requires-Dist: setuptools
Requires-Dist: fancylogging>=0.0.3
Dynamic: license-file
